level3/verilator1/alu.sv
typedef enum logic [1:0] {
	add = 2'h1,
	sub = 2'h2,
	nop = 2'h0
} operation_t;

module alu #(parameter WIDTH = 6)
(
	input clk,
	input rst,

	input operation_t op_in,
	input [WIDTH-1:0] a_in,
	input [WIDTH-1:0] b_in,
	input 		  in_valid,

	output logic [WIDTH-1:0] out,
	output logic             out_valid
);

	operation_t op_in_r;
	logic [WIDTH-1:0] a_in_r;
	logic [WIDTH-1:0] b_in_r;
	logic             in_valid_r;
	logic [WIDTH-1:0] result;

	always_ff @(posedge clk, posedge rst) begin
		if(rst) begin
			op_in_r<='0;
			a_in_r<='0;
			b_in_r <= '0;
			in_valid_r <= '0;
		end else begin
			op_in_r<=op_in;
			a_in_r<=a_in;
			b_in_r<=b_in;
			in_valid_r<=in_valid;
		end
	end

	always_comb begin
		result = '0;
		if(in_valid_r) begin
			case(op_in_r)
				add: result = a_in_r+b_in_r;
				sub:result = a_in_r +(~b_in_r+1'b1);
				default:result = '0;
			endcase
		end
	end

	always_ff @(posedge clk, posedge rst) begin
		if(rst) begin
			out <= '0;
			out_valid <= '0;
		end else begin
			out <= result;
			out_valid <= in_valid_r;
		end
	end
	endmodule;

level3/verilator1/waveform.vcd
$version Generated by VerilatedVcd $end
$date Wed Jun 26 23:41:33 2024
 $end
$timescale   1ps $end

 $scope module TOP $end
  $var wire  6 + a_in [5:0] $end
  $var wire  6 , b_in [5:0] $end
  $var wire  1 ( clk $end
  $var wire  1 - in_valid $end
  $var wire  2 * op_in [1:0] $end
  $var wire  6 . out [5:0] $end
  $var wire  1 / out_valid $end
  $var wire  1 ) rst $end
  $scope module alu $end
   $var wire 32 0 WIDTH [31:0] $end
   $var wire  6 + a_in [5:0] $end
   $var wire  6 $ a_in_r [5:0] $end
   $var wire  6 , b_in [5:0] $end
   $var wire  6 % b_in_r [5:0] $end
   $var wire  1 ( clk $end
   $var wire  1 - in_valid $end
   $var wire  1 & in_valid_r $end
   $var wire  2 * op_in [1:0] $end
   $var wire  2 # op_in_r [1:0] $end
   $var wire  6 . out [5:0] $end
   $var wire  1 / out_valid $end
   $var wire  6 ' result [5:0] $end
   $var wire  1 ) rst $end
  $upscope $end
 $upscope $end
$enddefinitions $end


#0
b01 #
b111000 $
b101001 %
0&
b000000 '
0(
0)
b10 *
b010001 +
b001011 ,
0-
b110011 .
1/
b00000000000000000000000000000110 0
#1
b10 #
b010001 $
b001011 %
1(
b000000 .
0/
#2
0(
#3
b00 #
b000000 $
b000000 %
1(
1)
b00 *
b000000 +
b000000 ,
#4
0(
#5
1(
#6
0(
0)
#7
1(
#8
0(
#9
1(
#10
0(
#11
1(
#12
0(
#13
1(
#14
0(
#15
1(
#16
0(
#17
1(
#18
0(
#19
1(
#20
0(
#21
1(
#22
0(
#23
1(
#24
0(
#25
1(
#26
0(
#27
1(
#28
0(
#29
1(
#30
0(
#31
1(
#32
0(
#33
1(
#34
0(
#35
1(
#36
0(
#37
1(
b01 *
b001101 +
b000010 ,
1-
#38
0(
#39
b01 #
b001101 $
b000010 %
1&
b001111 '
1(
b10 *
b001100 +
b000100 ,
#40
0(
#41
b10 #
b001100 $
b000100 %
b001000 '
1(
0-
b001111 .
1/
#42
0(
#43
0&
b000000 '
1(
b001000 .
#44
0(
#45
1(
b000000 .
0/
#46
0(
#47
1(
#48
0(
#49
1(
#50
0(
#51
1(
#52
0(
#53
1(
b01 *
b010001 +
1-
#54
0(
#55
b01 #
b010001 $
1&
b010101 '
1(
0-
#56
0(
#57
0&
b000000 '
1(
b010101 .
1/
#58
0(
#59
1(
b10 *
b010000 +
b000001 ,
1-
b000000 .
0/
#60
0(
#61
b10 #
b010000 $
b000001 %
1&
b001111 '
1(
0-
#62
0(
#63
0&
b000000 '
1(
b001111 .
1/
#64
0(
#65
1(
b000000 .
0/
#66
0(
#67
1(
#68
0(
#69
1(
#70
0(
#71
1(
b010011 +
b000011 ,
1-
#72
0(
#73
b010011 $
b000011 %
1&
b010000 '
1(
0-
#74
0(
#75
0&
b000000 '
1(
b010000 .
1/
#76
0(
#77
1(
b000000 .
0/
#78
0(
#79
1(
#80
0(
#81
1(
#82
0(
#83
1(
#84
0(
#85
1(
#86
0(
#87
1(
b01 *
b001111 +
b000100 ,
1-
#88
0(
#89
b01 #
b001111 $
b000100 %
1&
b010011 '
1(
0-
#90
0(
#91
0&
b000000 '
1(
b010011 .
1/
#92
0(
#93
1(
b000000 .
0/
#94
0(
#95
1(
#96
0(
#97
1(
#98
0(
#99
1(
#100
0(
#101
1(
#102
0(
#103
1(
#104
0(
#105
1(
#106
0(
#107
1(
#108
0(
#109
1(
#110
0(
#111
1(
#112
0(
#113
1(
#114
0(
#115
1(
#116
0(
#117
1(
b10 *
b001010 +
1-
#118
0(
#119
b10 #
b001010 $
1&
b000110 '
1(
0-
#120
0(
#121
0&
b000000 '
1(
b000110 .
1/
#122
0(
#123
1(
b01 *
b001100 +
b000101 ,
1-
b000000 .
0/
#124
0(
#125
b01 #
b001100 $
b000101 %
1&
b010001 '
1(
b001101 +
b000000 ,
#126
0(
#127
b001101 $
b000000 %
b001101 '
1(
0-
b010001 .
1/
#128
0(
#129
0&
b000000 '
1(
b001110 +
b000011 ,
1-
b001101 .
#130
0(
#131
b001110 $
b000011 %
1&
b010001 '
1(
0-
b000000 .
0/
#132
0(
#133
0&
b000000 '
1(
b010001 .
1/
#134
0(
#135
1(
b000000 .
0/
#136
0(
#137
1(
#138
0(
#139
1(
#140
0(
#141
1(
#142
0(
#143
1(
#144
0(
#145
1(
b001111 +
b000010 ,
1-
#146
0(
#147
b001111 $
b000010 %
1&
b010001 '
1(
b001100 +
#148
0(
#149
b001100 $
b001110 '
1(
0-
b010001 .
1/
#150
0(
#151
0&
b000000 '
1(
b001110 .
#152
0(
#153
1(
b000000 .
0/
